{
  "api": {
    "kakaologin": {
      "dependsOn": [
        {
          "attributes": [
            "Name",
            "Arn"
          ],
          "category": "function",
          "resourceName": "kakaologin"
        }
      ],
      "providerPlugin": "awscloudformation",
      "service": "API Gateway"
    },
    "saenggibuapp": {
      "dependsOn": [],
      "output": {
        "authConfig": {
          "additionalAuthenticationProviders": [],
          "defaultAuthentication": {
            "apiKeyConfig": {
              "apiKeyExpirationDate": "2023-01-30T07:48:26.542Z",
              "apiKeyExpirationDays": 7,
              "description": ""
            },
            "authenticationType": "API_KEY"
          }
        }
      },
      "providerPlugin": "awscloudformation",
      "service": "AppSync"
    }
  },
  "auth": {
    "saenggibuappe043b41f": {
      "customAuth": false,
      "dependsOn": [
        {
          "attributes": [
            "Arn",
            "Name"
          ],
          "category": "function",
          "resourceName": "saenggibuappe043b41fPostConfirmation",
          "triggerProvider": "Cognito"
        },
        {
          "attributes": [
            "Arn",
            "Name"
          ],
          "category": "function",
          "resourceName": "saenggibuappe043b41fPreSignup",
          "triggerProvider": "Cognito"
        }
      ],
      "frontendAuthConfig": {
        "mfaConfiguration": "OFF",
        "mfaTypes": [
          "SMS"
        ],
        "passwordProtectionSettings": {
          "passwordPolicyCharacters": [],
          "passwordPolicyMinLength": 8
        },
        "signupAttributes": [
          "EMAIL"
        ],
        "socialProviders": [],
        "usernameAttributes": [],
        "verificationMechanisms": [
          "EMAIL"
        ]
      },
      "providerPlugin": "awscloudformation",
      "service": "Cognito"
    },
    "userPoolGroups": {
      "dependsOn": [
        {
          "attributes": [
            "UserPoolId",
            "AppClientIDWeb",
            "AppClientID",
            "IdentityPoolId"
          ],
          "category": "auth",
          "resourceName": "saenggibuappe043b41f"
        }
      ],
      "providerPlugin": "awscloudformation",
      "service": "Cognito-UserPool-Groups"
    }
  },
  "function": {
    "kakaologin": {
      "build": true,
      "dependsOn": [],
      "providerPlugin": "awscloudformation",
      "service": "Lambda"
    },
    "saenggibuappe043b41fPostConfirmation": {
      "build": true,
      "providerPlugin": "awscloudformation",
      "service": "Lambda"
    },
    "saenggibuappe043b41fPreSignup": {
      "build": true,
      "providerPlugin": "awscloudformation",
      "service": "Lambda"
    }
  },
  "hosting": {},
  "parameters": {
    "AMPLIFY_function_kakaologin_deploymentBucketName": {
      "usedBy": [
        {
          "category": "function",
          "resourceName": "kakaologin"
        }
      ]
    },
    "AMPLIFY_function_kakaologin_s3Key": {
      "usedBy": [
        {
          "category": "function",
          "resourceName": "kakaologin"
        }
      ]
    },
    "AMPLIFY_function_saenggibuappe043b41fPostConfirmation_deploymentBucketName": {
      "usedBy": [
        {
          "category": "function",
          "resourceName": "saenggibuappe043b41fPostConfirmation"
        }
      ]
    },
    "AMPLIFY_function_saenggibuappe043b41fPostConfirmation_s3Key": {
      "usedBy": [
        {
          "category": "function",
          "resourceName": "saenggibuappe043b41fPostConfirmation"
        }
      ]
    },
    "AMPLIFY_function_saenggibuappe043b41fPreSignup_deploymentBucketName": {
      "usedBy": [
        {
          "category": "function",
          "resourceName": "saenggibuappe043b41fPreSignup"
        }
      ]
    },
    "AMPLIFY_function_saenggibuappe043b41fPreSignup_s3Key": {
      "usedBy": [
        {
          "category": "function",
          "resourceName": "saenggibuappe043b41fPreSignup"
        }
      ]
    }
  }
}